ComposeIt/Option.py
ComposeIt/Parser.py
ComposeIt/__init__.py
ComposeIt-1.0.0.dist-info/LICENSE
ComposeIt-1.0.0.dist-info/METADATA
ComposeIt-1.0.0.dist-info/WHEEL
ComposeIt-1.0.0.dist-info/entry_points.txt
ComposeIt-1.0.0.dist-info/top_level.txt
ComposeIt-1.0.0.dist-info/RECORD
