Metadata-Version: 2.1
Name: ComposeIt
Version: 1.0.0
Summary: Generate docker-compose file from existing containers
Home-page: https://github.com/sithladyraven/ComposeIt
Author: Kelsey Price
Author-email: kelsey@raven.ws
License: UNKNOWN
Platform: UNKNOWN
Classifier: Programming Language :: Python :: 3
Classifier: License :: OSI Approved :: MIT License
Classifier: Operating System :: OS Independent
Requires-Dist: docker (>=3.3.0)
Requires-Dist: pyyaml (>=3.12)
